mkdocstrings_handlers/zvm/__init__.py
mkdocstrings_handlers/zvm/handler.py
zvm/__init__.py
zvm/_version.py
zvm/cli.py
zvm/zvm.py
zvm-6.0.0.dist-info/LICENSE
zvm-6.0.0.dist-info/METADATA
zvm-6.0.0.dist-info/WHEEL
zvm-6.0.0.dist-info/entry_points.txt
zvm-6.0.0.dist-info/top_level.txt
zvm-6.0.0.dist-info/RECORD
