Metadata-Version: 2.1
Name: zvm
Version: 6.0.0
Summary: A virtual stack machine that executes Python code based on instructions provided in a JSON file.
Home-page: https://github.com/ieg-tech/zvm.git
License-File: LICENSE
Provides-Extra: develop
Requires-Dist: flake8 ; extra == 'develop'
Requires-Dist: pytest ; extra == 'develop'
Provides-Extra: docs
Requires-Dist: mkdocs ; extra == 'docs'
Requires-Dist: mkdocstrings[python] ; extra == 'docs'
Requires-Dist: mkdocs-terminal ; extra == 'docs'
